<?xml version="1.0" encoding="utf-8"?>
<helpItems schema="maml" xmlns="http://msh">
  <command:command xmlns:maml="http://schemas.microsoft.com/maml/2004/10" xmlns:command="http://schemas.microsoft.com/maml/dev/command/2004/10" xmlns:dev="http://schemas.microsoft.com/maml/dev/2004/10" xmlns:MSHelp="http://msdn.microsoft.com/mshelp">
    <command:details>
      <command:name>Convert-SSHRegistryToJSonKnownHost</command:name>
      <command:verb>Convert</command:verb>
      <command:noun>SSHRegistryToJSonKnownHost</command:noun>
      <maml:description>
        <maml:para>Convert windows registry key storage to Json</maml:para>
      </maml:description>
    </command:details>
    <maml:description>
      <maml:para>Convert windows registry key storage to Json It is windows-only compatibility cmdlet</maml:para>
    </maml:description>
    <command:syntax>
      <command:syntaxItem>
        <maml:name>Convert-SSHRegistryToJSonKnownHost</maml:name>
      </command:syntaxItem>
    </command:syntax>
    <command:parameters />
    <command:inputTypes />
    <command:returnValues />
    <maml:alertSet>
      <maml:alert>
        <maml:para></maml:para>
      </maml:alert>
    </maml:alertSet>
    <command:examples>
      <command:example>
        <maml:title>-------------------------- Example 1 --------------------------</maml:title>
        <dev:code>PS C:\&gt; {{ Add example code here }}</dev:code>
        <dev:remarks>
          <maml:para>{{ Add example description here }}</maml:para>
        </dev:remarks>
      </command:example>
    </command:examples>
    <command:relatedLinks />
  </command:command>
  <command:command xmlns:maml="http://schemas.microsoft.com/maml/2004/10" xmlns:command="http://schemas.microsoft.com/maml/dev/command/2004/10" xmlns:dev="http://schemas.microsoft.com/maml/dev/2004/10" xmlns:MSHelp="http://msdn.microsoft.com/mshelp">
    <command:details>
      <command:name>Get-SSHRegistryKnownHost</command:name>
      <command:verb>Get</command:verb>
      <command:noun>SSHRegistryKnownHost</command:noun>
      <maml:description>
        <maml:para>Get KnownHosts from registry (readonly)</maml:para>
      </maml:description>
    </command:details>
    <maml:description>
      <maml:para>Get KnownHosts from registry (readonly) It is windows-only compatibility cmdlet</maml:para>
    </maml:description>
    <command:syntax>
      <command:syntaxItem>
        <maml:name>Get-SSHRegistryKnownHost</maml:name>
      </command:syntaxItem>
    </command:syntax>
    <command:parameters />
    <command:inputTypes />
    <command:returnValues />
    <maml:alertSet>
      <maml:alert>
        <maml:para></maml:para>
      </maml:alert>
    </maml:alertSet>
    <command:examples>
      <command:example>
        <maml:title>-------------------------- Example 1 --------------------------</maml:title>
        <dev:code>PS C:\&gt; {{ Add example code here }}</dev:code>
        <dev:remarks>
          <maml:para>{{ Add example description here }}</maml:para>
        </dev:remarks>
      </command:example>
    </command:examples>
    <command:relatedLinks>
      <maml:navigationLink>
        <maml:linkText>Online Version:</maml:linkText>
        <maml:uri>https://github.com/darkoperator/Posh-SSH/tree/master/docs</maml:uri>
      </maml:navigationLink>
    </command:relatedLinks>
  </command:command>
</helpItems>